[
  {
    "name": "Анархо-Коммунизм",
    "stats": {
      "dipl": 50,
      "econ": 100,
      "govt": 100,
      "scty": 90
    }
  },
  {
    "name": "Либертарный Коммунизм",
    "stats": {
      "dipl": 70,
      "econ": 100,
      "govt": 80,
      "scty": 80
    }
  },
  {
    "name": "Троцкизм",
    "stats": {
      "dipl": 100,
      "econ": 100,
      "govt": 60,
      "scty": 80
    }
  },
  {
    "name": "Марксизм",
    "stats": {
      "dipl": 70,
      "econ": 100,
      "govt": 40,
      "scty": 80
    }
  },
  {
    "name": "Де Леонизм",
    "stats": {
      "dipl": 30,
      "econ": 100,
      "govt": 30,
      "scty": 80
    }
  },
  {
    "name": "Ленинизм",
    "stats": {
      "dipl": 40,
      "econ": 100,
      "govt": 20,
      "scty": 70
    }
  },
  {
    "name": "Сталинизм/Маоизм",
    "stats": {
      "dipl": 20,
      "econ": 100,
      "govt": 0,
      "scty": 60
    }
  },
  {
    "name": "Религиозный Коммунизм",
    "stats": {
      "dipl": 50,
      "econ": 100,
      "govt": 30,
      "scty": 30
    }
  },
  {
    "name": "Государственный Социализм",
    "stats": {
      "dipl": 30,
      "econ": 80,
      "govt": 30,
      "scty": 70
    }
  },
  {
    "name": "Теократический Социализм",
    "stats": {
      "dipl": 50,
      "econ": 80,
      "govt": 30,
      "scty": 20
    }
  },
  {
    "name": "Религиозный Социализм",
    "stats": {
      "dipl": 50,
      "econ": 80,
      "govt": 70,
      "scty": 20
    }
  },
  {
    "name": "Демократический Социализм",
    "stats": {
      "dipl": 50,
      "econ": 80,
      "govt": 50,
      "scty": 80
    }
  },
  {
    "name": "Революционный Социализм",
    "stats": {
      "dipl": 20,
      "econ": 80,
      "govt": 50,
      "scty": 70
    }
  },
  {
    "name": "Либертарный Социализм",
    "stats": {
      "dipl": 80,
      "econ": 80,
      "govt": 80,
      "scty": 80
    }
  },
  {
    "name": "Анархо-Синдикализм",
    "stats": {
      "dipl": 50,
      "econ": 80,
      "govt": 100,
      "scty": 80
    }
  },
  {
    "name": "Популизм Левого крыла",
    "stats": {
      "dipl": 40,
      "econ": 60,
      "govt": 30,
      "scty": 70
    }
  },
  {
    "name": "Теократический Дистрибутизм",
    "stats": {
      "dipl": 40,
      "econ": 60,
      "govt": 30,
      "scty": 20
    }
  },
  {
    "name": "Дистрибутизм",
    "stats": {
      "dipl": 50,
      "econ": 60,
      "govt": 50,
      "scty": 20
    }
  },
  {
    "name": "Социал-Либерализм",
    "stats": {
      "dipl": 60,
      "econ": 60,
      "govt": 60,
      "scty": 80
    }
  },
  {
    "name": "Христианская Демократия",
    "stats": {
      "dipl": 60,
      "econ": 60,
      "govt": 40,
      "scty": 30
    }
  },
  {
    "name": "Социальная Демократия",
    "stats": {
      "dipl": 70,
      "econ": 60,
      "govt": 40,
      "scty": 80
    }
  },
  {
    "name": "Прогрессивизм",
    "stats": {
      "dipl": 80,
      "econ": 60,
      "govt": 60,
      "scty": 100
    }
  },
  {
    "name": "Анархо-Мютюэлизм",
    "stats": {
      "dipl": 50,
      "econ": 60,
      "govt": 100,
      "scty": 70
    }
  },
  {
    "name": "Национальный Тоталитаризм",
    "stats": {
      "dipl": 20,
      "econ": 50,
      "govt": 0,
      "scty": 50
    }
  },
  {
    "name": "Глобальный Тоталитаризм",
    "stats": {
      "dipl": 80,
      "econ": 50,
      "govt": 0,
      "scty": 50
    }
  },
  {
    "name": "Технократия",
    "stats": {
      "dipl": 60,
      "econ": 60,
      "govt": 20,
      "scty": 70
    }
  },
  {
    "name": "Центризм",
    "stats": {
      "dipl": 50,
      "econ": 50,
      "govt": 50,
      "scty": 50
    }
  },
  {
    "name": "Либерализм",
    "stats": {
      "dipl": 60,
      "econ": 50,
      "govt": 60,
      "scty": 60
    }
  },
  {
    "name": "Религиозный Анархизм",
    "stats": {
      "dipl": 50,
      "econ": 50,
      "govt": 100,
      "scty": 20
    }
  },
  {
    "name": "Популизм Правого крыла",
    "stats": {
      "dipl": 30,
      "econ": 40,
      "govt": 30,
      "scty": 30
    }
  },
  {
    "name": "Современный Консерватизм",
    "stats": {
      "dipl": 40,
      "econ": 40,
      "govt": 50,
      "scty": 30
    }
  },
  {
    "name": "Реакционизм",
    "stats": {
      "dipl": 40,
      "econ": 40,
      "govt": 40,
      "scty": 10
    }
  },
  {
    "name": "Либертарный Социализм",
    "stats": {
      "dipl": 70,
      "econ": 60,
      "govt": 80,
      "scty": 70
    }
  },
  {
    "name": "Либертарианство",
    "stats": {
      "dipl": 60,
      "econ": 40,
      "govt": 80,
      "scty": 60
    }
  },
  {
    "name": "Анархо-Эгоизм",
    "stats": {
      "dipl": 50,
      "econ": 40,
      "govt": 100,
      "scty": 50
    }
  },
  {
    "name": "Нацизм",
    "stats": {
      "dipl": 0,
      "econ": 40,
      "govt": 0,
      "scty": 5
    }
  },
  {
    "name": "Автократия",
    "stats": {
      "dipl": 20,
      "econ": 50,
      "govt": 20,
      "scty": 50
    }
  },
  {
    "name": "Фашизм",
    "stats": {
      "dipl": 20,
      "econ": 40,
      "govt": 20,
      "scty": 20
    }
  },
  {
    "name": "Капиталистический Фашизм",
    "stats": {
      "dipl": 20,
      "econ": 20,
      "govt": 20,
      "scty": 20
    }
  },
  {
    "name": "Консерватизм",
    "stats": {
      "dipl": 40,
      "econ": 30,
      "govt": 40,
      "scty": 20
    }
  },
  {
    "name": "Нео-Либерализм",
    "stats": {
      "dipl": 30,
      "econ": 30,
      "govt": 50,
      "scty": 60
    }
  },
  {
    "name": "Классический Либерализм",
    "stats": {
      "dipl": 60,
      "econ": 30,
      "govt": 60,
      "scty": 80
    }
  },
  {
    "name": "Авторитарный Капитализм",
    "stats": {
      "dipl": 30,
      "econ": 20,
      "govt": 20,
      "scty": 40
    }
  },
  {
    "name": "Государственный Капитализм",
    "stats": {
      "dipl": 50,
      "econ": 20,
      "govt": 30,
      "scty": 50
    }
  },
  {
    "name": "Нео-Консерватизм",
    "stats": {
      "dipl": 20,
      "econ": 20,
      "govt": 40,
      "scty": 20
    }
  },
  {
    "name": "Фундаментализм",
    "stats": {
      "dipl": 30,
      "econ": 20,
      "govt": 30,
      "scty": 5
    }
  },
  {
    "name": "Либертарианский Капитализм",
    "stats": {
      "dipl": 50,
      "econ": 20,
      "govt": 80,
      "scty": 60
    }
  },
  {
    "name": "Анархизм Свободного Рынка",
    "stats": {
      "dipl": 50,
      "econ": 20,
      "govt": 100,
      "scty": 50
    }
  },
  {
    "name": "Тоталитарный Капитализм",
    "stats": {
      "dipl": 30,
      "econ": 0,
      "govt": 0,
      "scty": 50
    }
  },
  {
    "name": "Ультра-Капитализм",
    "stats": {
      "dipl": 40,
      "econ": 0,
      "govt": 50,
      "scty": 50
    }
  },
  {
    "name": "Анархо-Капитализм",
    "stats": {
      "dipl": 50,
      "econ": 0,
      "govt": 100,
      "scty": 50
    }
  }
]
